odoo/addons/l10n_be_bpost_address_autocomplete/README.rst
odoo/addons/l10n_be_bpost_address_autocomplete/__init__.py
odoo/addons/l10n_be_bpost_address_autocomplete/__manifest__.py
odoo/addons/l10n_be_bpost_address_autocomplete/i18n/l10n_be_bpost_address_autocomplete.pot
odoo/addons/l10n_be_bpost_address_autocomplete/models/__init__.py
odoo/addons/l10n_be_bpost_address_autocomplete/models/res_partner.py
odoo/addons/l10n_be_bpost_address_autocomplete/readme/CONTRIBUTORS.rst
odoo/addons/l10n_be_bpost_address_autocomplete/readme/DESCRIPTION.rst
odoo/addons/l10n_be_bpost_address_autocomplete/readme/HISTORY.rst
odoo/addons/l10n_be_bpost_address_autocomplete/readme/INSTALL.rst
odoo/addons/l10n_be_bpost_address_autocomplete/readme/USAGE.rst
odoo/addons/l10n_be_bpost_address_autocomplete/static/description/doc_create_contact.png
odoo/addons/l10n_be_bpost_address_autocomplete/static/description/doc_finish.png
odoo/addons/l10n_be_bpost_address_autocomplete/static/description/doc_on_autocomplete.png
odoo/addons/l10n_be_bpost_address_autocomplete/static/description/doc_on_click.png
odoo/addons/l10n_be_bpost_address_autocomplete/static/description/doc_on_new.png
odoo/addons/l10n_be_bpost_address_autocomplete/static/description/doc_on_search.png
odoo/addons/l10n_be_bpost_address_autocomplete/static/description/icon.png
odoo/addons/l10n_be_bpost_address_autocomplete/static/description/index.html
odoo/addons/l10n_be_bpost_address_autocomplete/static/lib/bp-address-auto-complete/bp-address-autocomplete-search-bar.js
odoo/addons/l10n_be_bpost_address_autocomplete/static/src/js/widget/bp_address_auto_complete/bp_address_auto_complete.esm.js
odoo/addons/l10n_be_bpost_address_autocomplete/static/src/js/widget/bp_address_auto_complete/bp_address_auto_complete.scss
odoo/addons/l10n_be_bpost_address_autocomplete/static/src/js/widget/bp_address_auto_complete/bp_address_auto_complete.xml
odoo/addons/l10n_be_bpost_address_autocomplete/tests/__init__.py
odoo_addon_l10n_be_bpost_address_autocomplete-16.0.1.0.1.dist-info/METADATA
odoo_addon_l10n_be_bpost_address_autocomplete-16.0.1.0.1.dist-info/WHEEL
odoo_addon_l10n_be_bpost_address_autocomplete-16.0.1.0.1.dist-info/top_level.txt
odoo_addon_l10n_be_bpost_address_autocomplete-16.0.1.0.1.dist-info/RECORD
