Metadata-Version: 2.1
Name: odoo-addon-l10n_be_bpost_address_autocomplete
Version: 16.0.1.0.1
Summary: Bpost address autocomplete
Home-page: https://github.com/OCA/l10n-belgium
Author: ACSONE SA/NV,Odoo Community Association (OCA)
Author-email: support@odoo-community.org
License: AGPL-3
Classifier: Programming Language :: Python
Classifier: Framework :: Odoo
Classifier: Framework :: Odoo :: 16.0
Classifier: License :: OSI Approved :: GNU Affero General Public License v3
Requires-Python: >=3.10
Requires-Dist: odoo<16.1dev,>=16.0a
